simple_env_setup/main.py
simple_env_setup/recipes/__init__.py
simple_env_setup/recipes/rust.py
simple_env_setup/recipes/zsh.py
simple_env_setup/resources/.gitconfig
simple_env_setup/resources/.shellrc
simple_env_setup/resources/.zshrc
simple_env_setup/resources/__init__.py
simple_env_setup/resources/starship.toml
simple_env_setup/utils/__init__.py
simple_env_setup/utils/rc.py
simple_env_setup/utils/utils.py
simple_env_setup-0.1.4.dist-info/entry_points.txt
simple_env_setup-0.1.4.dist-info/WHEEL
simple_env_setup-0.1.4.dist-info/METADATA
simple_env_setup-0.1.4.dist-info/RECORD
