Metadata-Version: 2.1
Name: simple-env-setup
Version: 0.1.4
Summary: Sets up the development environment to your (my) likings.
Author: Peter Yuen
Requires-Python: >=3.10,<4.0
Classifier: Programming Language :: Python :: 3
Classifier: Programming Language :: Python :: 3.10
Requires-Dist: click (>=8.0.3,<9.0.0)
Requires-Dist: shutils (>=0.1.0,<0.2.0)
Requires-Dist: termcolor (>=1.1.0,<2.0.0)
